easyqt/__init__.py
easyqt/utils.py
easyqt/button/__init__.py
easyqt/button/iconbutton.py
easyqt/dialog/__init__.py
easyqt/dialog/basicdialog.py
easyqt/dialog/confirmdialog.py
easyqt/dialog/infodialog.py
easyqt/dialog/progressdialog.py
easyqt/dialog/textinputdialog.py
easyqt/frame/__init__.py
easyqt/frame/toaster.py
easyqt/widget/__init__.py
easyqt/widget/basicwidget.py
easyqt/widget/buttongroupwidget.py
easyqt/widget/checkboxgroupwidget.py
easyqt/widget/collapsiblewidget.py
easyqt/widget/dockingwidget.py
easyqt/widget/dropdownwidget.py
easyqt/widget/fieldwidget.py
easyqt/widget/iconwidget.py
easyqt/widget/integerwidget.py
easyqt/widget/listwidget.py
easyqt/widget/loadingtextwidget.py
easyqt/widget/loginwidget.py
easyqt/widget/pinwidget.py
easyqt/widget/scrollarea.py
easyqt/widget/searchfieldwidget.py
easyqt/widget/separatorwidget.py
easyqt/widget/tablewidget.py
easyqt/widget/toolbarwidget.py
easyqt/window/__init__.py
easyqt/window/dockingwindow.py
easyqt/window/mainwindow.py
easyqt-0.3.dist-info/LICENSE
easyqt-0.3.dist-info/METADATA
easyqt-0.3.dist-info/WHEEL
easyqt-0.3.dist-info/top_level.txt
easyqt-0.3.dist-info/RECORD
