Metadata-Version: 2.1
Name: easyqt
Version: 0.3
Summary: A collection of custom built pyqt widgets and wrappers for quick, easy and fun GUI development
Author: Jonathan Mafi
Author-email: jmafi3d@gmail.com
Requires-Python: >=3.6
License-File: LICENSE
Requires-Dist: PyQt5
